run.py
otpsy/__init__.py
otpsy/additional_function.py
otpsy/config.py
otpsy/main.py
otpsy/mathematics.py
otpsy/threshold.py
otpsy/utils.py
otpsy/visualise/__init__.py
otpsy/visualise/app.py
otpsy/visualise/assets/__init__.py
otpsy/visualise/assets/style.css
otpsy-0.0.5.dist-info/LICENSE
otpsy-0.0.5.dist-info/METADATA
otpsy-0.0.5.dist-info/WHEEL
otpsy-0.0.5.dist-info/top_level.txt
otpsy-0.0.5.dist-info/RECORD
