Metadata-Version: 2.1
Name: otpsy
Version: 0.0.5
Summary: Packages designed to detect outliers in Social and Human Sciences
Author-email: Alexandre Lietard <alex.lietard77@gmail.com>
Project-URL: Homepage, https://github.com/AlexLietard/otpsy
Project-URL: Issues, https://github.com/AlexLietard/otpsy/issues
Classifier: Programming Language :: Python :: 3
Classifier: License :: OSI Approved :: MIT License
Classifier: Operating System :: OS Independent
Requires-Python: >=3.10
License-File: LICENSE
Requires-Dist: blinker
Requires-Dist: certifi
Requires-Dist: charset-normalizer
Requires-Dist: click
Requires-Dist: colorama
Requires-Dist: dash
Requires-Dist: dash-bootstrap-components
Requires-Dist: dash-bootstrap-templates
Requires-Dist: dash-core-components
Requires-Dist: dash-html-components
Requires-Dist: dash-table
Requires-Dist: Flask
Requires-Dist: itsdangerous
Requires-Dist: importlib-metadata
Requires-Dist: Jinja2
Requires-Dist: MarkupSafe
Requires-Dist: nest-asyncio
Requires-Dist: numpy
Requires-Dist: packaging
Requires-Dist: pandas
Requires-Dist: plotly
Requires-Dist: pyarrow
Requires-Dist: python-dateutil
Requires-Dist: pytz
Requires-Dist: requests
Requires-Dist: retrying
Requires-Dist: six
Requires-Dist: tenacity
Requires-Dist: typing-extensions
Requires-Dist: tzdata
Requires-Dist: urllib3
Requires-Dist: Werkzeug
Requires-Dist: zipp
